dissect/executable/__init__.py
dissect/executable/exception.py
dissect/executable/elf/__init__.py
dissect/executable/elf/c_elf.py
dissect/executable/elf/elf.py
dissect/executable/macho/__init__.py
dissect/executable/pe/__init__.py
dissect/executable/pe/c_pe.py
dissect/executable/pe/c_pe.pyi
dissect/executable/pe/locale_id.py
dissect/executable/pe/pe.py
dissect/executable/pe/directory/__init__.py
dissect/executable/pe/directory/base.py
dissect/executable/pe/directory/basereloc.py
dissect/executable/pe/directory/bound_import.py
dissect/executable/pe/directory/com_descriptor.py
dissect/executable/pe/directory/debug.py
dissect/executable/pe/directory/delay_import.py
dissect/executable/pe/directory/exception.py
dissect/executable/pe/directory/export.py
dissect/executable/pe/directory/iat.py
dissect/executable/pe/directory/imports.py
dissect/executable/pe/directory/load_config.py
dissect/executable/pe/directory/resource.py
dissect/executable/pe/directory/security.py
dissect/executable/pe/directory/tls.py
dissect_executable-1.10.dist-info/licenses/COPYRIGHT
dissect_executable-1.10.dist-info/licenses/LICENSE
dissect_executable-1.10.dist-info/METADATA
dissect_executable-1.10.dist-info/WHEEL
dissect_executable-1.10.dist-info/top_level.txt
dissect_executable-1.10.dist-info/RECORD
