Metadata-Version: 2.4
Name: dissect.executable
Version: 1.10
Summary: A Dissect module implementing a parsers for various executable formats such as PE, ELF and Macho-O
Author-email: Dissect Team <dissect@fox-it.com>
License-Expression: AGPL-3.0-or-later
Project-URL: homepage, https://dissect.tools
Project-URL: documentation, https://docs.dissect.tools/en/latest/projects/dissect.executable
Project-URL: repository, https://github.com/fox-it/dissect.executable
Classifier: Development Status :: 5 - Production/Stable
Classifier: Environment :: Console
Classifier: Intended Audience :: Developers
Classifier: Intended Audience :: Information Technology
Classifier: Operating System :: OS Independent
Classifier: Programming Language :: Python :: 3
Classifier: Topic :: Internet :: Log Analysis
Classifier: Topic :: Scientific/Engineering :: Information Analysis
Classifier: Topic :: Security
Classifier: Topic :: Utilities
Requires-Python: ~=3.9
License-File: LICENSE
License-File: COPYRIGHT
Requires-Dist: dissect.cstruct<5,>=4.6
Requires-Dist: dissect.util<4,>=3
Provides-Extra: dev
Requires-Dist: dissect.cstruct<5.0.dev,>=4.6.dev; extra == "dev"
Requires-Dist: dissect.util<4.0.dev,>=3.0.dev; extra == "dev"
Dynamic: license-file
